dws_merkle/Base.py
dws_merkle/__init__.py
dws_merkle/common.py
dws_merkle/merkleTree.py
dws_merkle-0.0.7.dist-info/LICENSE.rst
dws_merkle-0.0.7.dist-info/METADATA
dws_merkle-0.0.7.dist-info/WHEEL
dws_merkle-0.0.7.dist-info/top_level.txt
dws_merkle-0.0.7.dist-info/RECORD
