Metadata-Version: 2.1
Name: dws-merkle
Version: 0.0.7
Summary: dws-merkle
Home-page: UNKNOWN
Author: Dcentralab (Niv Shitrit)
Author-email: <niv@dcentralab.com>
License: MIT
Keywords: python
Platform: UNKNOWN
Classifier: Development Status :: 1 - Planning
Classifier: Intended Audience :: Developers
Classifier: Programming Language :: Python :: 3
Classifier: Operating System :: Unix
Classifier: Operating System :: MacOS :: MacOS X
Classifier: Operating System :: Microsoft :: Windows
License-File: LICENSE.rst
Requires-Dist: requests
